<?xml version="1.0"?>
<col:collection xmlns="http://cnx.rice.edu/collxml"
                xmlns:cnx="http://cnx.rice.edu/cnxml"
                xmlns:cnxorg="http://cnx.rice.edu/system-info"
                xmlns:md="http://cnx.rice.edu/mdml"
                xmlns:col="http://cnx.rice.edu/collxml"
                xmlns:cnxml="http://cnx.rice.edu/cnxml"
                xmlns:m="http://www.w3.org/1998/Math/MathML"
                xmlns:q="http://cnx.rice.edu/qml/1.0"
                xmlns:xhtml="http://www.w3.org/1999/xhtml"
                xmlns:bib="http://bibtexml.sf.net/"
                xmlns:cc="http://web.resource.org/cc/"
                xmlns:rdf="http://www.w3.org/1999/02/22-rdf-syntax-ns#"
                xml:lang="en">
  <metadata xmlns:md="http://cnx.rice.edu/mdml"
          mdml-version="0.5">
  <!-- WARNING! The 'metadata' section is read only. Do not edit below.
       Changes to the metadata section in the source will not be saved. -->

  <md:repository>https://legacy.cnx.org/content</md:repository>
  <md:content-url>https://legacy.cnx.org/content/col11756/1.13</md:content-url>
  <md:content-id>col11756</md:content-id>
  <md:title>Prealgebra</md:title>
  
  
  <md:version>1.13</md:version>
  <md:created>2015/01/27 01:43:54.710 GMT-6</md:created>
  <md:revised>2018/07/30 10:58:45.839 GMT-5</md:revised>

  <md:actors>
    
    <md:organization userid="OpenStaxCollege">
      <md:shortname>OpenStax</md:shortname>
      <md:fullname>OpenStax</md:fullname>
      <md:email>info@openstax.org</md:email>
    </md:organization>
    
    
    
    
    <md:person userid="OSCRiceUniversity">
      <md:firstname>Rice</md:firstname>
      <md:surname>University</md:surname>
      <md:fullname>Rice University</md:fullname>
      <md:email>info@openstaxcollege.org</md:email>
    </md:person>
    
    
    
    <md:person userid="cnxbasicmath">
      <md:firstname>Openstax</md:firstname>
      <md:surname>Basic Math</md:surname>
      <md:fullname>Openstax Prealgabra</md:fullname>
      <md:email>info@openstaxcollege.org</md:email>
    </md:person>
    
  </md:actors>
  <md:roles>
    <md:role type="author">OpenStaxCollege</md:role>
    <md:role type="maintainer">OpenStaxCollege cnxbasicmath</md:role>
    <md:role type="licensor">OSCRiceUniversity</md:role>
    
    
  </md:roles>

  <md:license url="http://creativecommons.org/licenses/by/4.0/">Creative Commons Attribution License 4.0</md:license>
  <!-- For information on license requirements for use or modification, see license url in the
       above <md:license> element.
       For information on formatting required attribution, see the URL:
         CONTENT_URL/content_info#cnx_cite_header
       where CONTENT_URL is the value provided above in the <md:content-url> element.
  -->
  
  
  
  

  

  

  <md:subjectlist>
    <md:subject>Mathematics and Statistics</md:subject>
  </md:subjectlist>

  <md:abstract></md:abstract>

  <md:language>en</md:language>

  

  
  
  
  
  

  <!-- WARNING! The 'metadata' section is read only. Do not edit above.
       Changes to the metadata section in the source will not be saved. -->
</metadata>

  <col:parameters>
    <col:param name="real-imaginary-notation" value="font"/>
    <col:param name="and-or-notation"
               value="propositional-logic"/>
    <col:param name="gradient-notation" value="text"/>
    <col:param name="mean-notation" value="bar"/>
    <col:param name="remainder-notation" value="text"/>
    <col:param name="conjugate-notation" value="bar"/>
    <col:param name="imaginary-i-notation" value="i"/>
    <col:param name="scalar-product-notation"
               value="angle-bracket"/>
    <col:param name="print-font-size" value="10pt"/>
    <col:param name="curl-notation" value="text"/>
    <col:param name="for-all-equation-layout"
               value="symbolic"/>
    <col:param name="vector-notation" value="bold"/>
    <col:param name="print-paper-size" value="8.5x11"/>
    <col:param name="print-font" value="computer-modern"/>
    <col:param name="print-style"
               value="ccap-developmental-math"/>
    <col:param name="print-paragraph-spacing"
               value="compact"/>
  </col:parameters>
  
  <col:content>
    
      <col:module document="m57828" version="latest"
                  repository="https://legacy.cnx.org/content"
                  cnxorg:version-at-this-collection-version="1.23">
        <md:title>Preface</md:title>
        
        
        
      </col:module>
        
      
    
    
      
        
      <col:subcollection>
        <md:title>Whole Numbers</md:title>
        
        
        

        <col:content>
          
    
      <col:module document="m57792" version="latest"
                  repository="https://legacy.cnx.org/content"
                  cnxorg:version-at-this-collection-version="1.6">
        <md:title>Introduction</md:title>
        
        
        
      </col:module>
        
      
    
    
      <col:module document="m52990" version="latest"
                  repository="https://legacy.cnx.org/content"
                  cnxorg:version-at-this-collection-version="1.14">
        <md:title>Introduction to Whole Numbers</md:title>
        
        
        
      </col:module>
        
      
    
    
      <col:module document="m52993" version="latest"
                  repository="https://legacy.cnx.org/content"
                  cnxorg:version-at-this-collection-version="1.14">
        <md:title>Add Whole Numbers</md:title>
        
        
        
      </col:module>
        
      
    
    
      <col:module document="m52995" version="latest"
                  repository="https://legacy.cnx.org/content"
                  cnxorg:version-at-this-collection-version="1.18">
        <md:title>Subtract Whole Numbers</md:title>
        
        
        
      </col:module>
        
      
    
    
      <col:module document="m52998" version="latest"
                  repository="https://legacy.cnx.org/content"
                  cnxorg:version-at-this-collection-version="1.18">
        <md:title>Multiply Whole Numbers</md:title>
        
        
        
      </col:module>
        
      
    
    
      <col:module document="m53001" version="latest"
                  repository="https://legacy.cnx.org/content"
                  cnxorg:version-at-this-collection-version="1.25">
        <md:title>Divide Whole Numbers</md:title>
        
        
        
      </col:module>
        
      
    
        </col:content>
      </col:subcollection>
    
    
      
        
      <col:subcollection>
        <md:title>The Language of Algebra</md:title>
        
        
        

        <col:content>
          
    
      <col:module document="m57793" version="latest"
                  repository="https://legacy.cnx.org/content"
                  cnxorg:version-at-this-collection-version="1.5">
        <md:title>Introduction to the Language of Algebra</md:title>
        
        
        
      </col:module>
        
      
    
    
      <col:module document="m53002" version="latest"
                  repository="https://legacy.cnx.org/content"
                  cnxorg:version-at-this-collection-version="1.18">
        <md:title>Use the Language of Algebra</md:title>
        
        
        
      </col:module>
        
      
    
    
      <col:module document="m53005" version="latest"
                  repository="https://legacy.cnx.org/content"
                  cnxorg:version-at-this-collection-version="1.19">
        <md:title>Evaluate, Simplify, and Translate Expressions</md:title>
        
        
        
      </col:module>
        
      
    
    
      <col:module document="m53006" version="latest"
                  repository="https://legacy.cnx.org/content"
                  cnxorg:version-at-this-collection-version="1.21">
        <md:title>Solving Equations Using the Subtraction and Addition Properties of Equality</md:title>
        
        
        
      </col:module>
        
      
    
    
      <col:module document="m53009" version="latest"
                  repository="https://legacy.cnx.org/content"
                  cnxorg:version-at-this-collection-version="1.17">
        <md:title>Find Multiples and Factors</md:title>
        
        
        
      </col:module>
        
      
    
    
      <col:module document="m53011" version="latest"
                  repository="https://legacy.cnx.org/content"
                  cnxorg:version-at-this-collection-version="1.23">
        <md:title>Prime Factorization and the Least Common Multiple</md:title>
        
        
        
      </col:module>
        
      
    
        </col:content>
      </col:subcollection>
    
    
      
        
      <col:subcollection>
        <md:title>Integers</md:title>
        
        
        

        <col:content>
          
    
      <col:module document="m57794" version="latest"
                  repository="https://legacy.cnx.org/content"
                  cnxorg:version-at-this-collection-version="1.5">
        <md:title>Introduction to Integers</md:title>
        
        
        
      </col:module>
        
      
    
    
      <col:module document="m53018" version="latest"
                  repository="https://legacy.cnx.org/content"
                  cnxorg:version-at-this-collection-version="1.22">
        <md:title>Introduction to Integers</md:title>
        
        
        
      </col:module>
        
      
    
    
      <col:module document="m53013" version="latest"
                  repository="https://legacy.cnx.org/content"
                  cnxorg:version-at-this-collection-version="1.21">
        <md:title>Add Integers</md:title>
        
        
        
      </col:module>
        
      
    
    
      <col:module document="m53027" version="latest"
                  repository="https://legacy.cnx.org/content"
                  cnxorg:version-at-this-collection-version="1.25">
        <md:title>Subtract Integers</md:title>
        
        
        
      </col:module>
        
      
    
    
      <col:module document="m53022" version="latest"
                  repository="https://legacy.cnx.org/content"
                  cnxorg:version-at-this-collection-version="1.19">
        <md:title>Multiply and Divide Integers</md:title>
        
        
        
      </col:module>
        
      
    
    
      <col:module document="m53025" version="latest"
                  repository="https://legacy.cnx.org/content"
                  cnxorg:version-at-this-collection-version="1.20">
        <md:title>Solve Equations Using Integers; The Division Property of Equality</md:title>
        
        
        
      </col:module>
        
      
    
        </col:content>
      </col:subcollection>
    
    
      
        
      <col:subcollection>
        <md:title>Fractions</md:title>
        
        
        

        <col:content>
          
    
      <col:module document="m57795" version="latest"
                  repository="https://legacy.cnx.org/content"
                  cnxorg:version-at-this-collection-version="1.5">
        <md:title>Introduction to Fractions</md:title>
        
        
        
      </col:module>
        
      
    
    
      <col:module document="m53036" version="latest"
                  repository="https://legacy.cnx.org/content"
                  cnxorg:version-at-this-collection-version="1.19">
        <md:title>Visualize Fractions</md:title>
        
        
        
      </col:module>
        
      
    
    
      <col:module document="m53030" version="latest"
                  repository="https://legacy.cnx.org/content"
                  cnxorg:version-at-this-collection-version="1.20">
        <md:title>Multiply and Divide Fractions</md:title>
        
        
        
      </col:module>
        
      
    
    
      <col:module document="m53038" version="latest"
                  repository="https://legacy.cnx.org/content"
                  cnxorg:version-at-this-collection-version="1.16">
        <md:title>Multiply and Divide Mixed Numbers and Complex Fractions</md:title>
        
        
        
      </col:module>
        
      
    
    
      <col:module document="m53042" version="latest"
                  repository="https://legacy.cnx.org/content"
                  cnxorg:version-at-this-collection-version="1.15">
        <md:title>Add and Subtract Fractions with Common Denominators</md:title>
        
        
        
      </col:module>
        
      
    
    
      <col:module document="m53041" version="latest"
                  repository="https://legacy.cnx.org/content"
                  cnxorg:version-at-this-collection-version="1.16">
        <md:title>Add and Subtract Fractions with Different Denominators</md:title>
        
        
        
      </col:module>
        
      
    
    
      <col:module document="m53026" version="latest"
                  repository="https://legacy.cnx.org/content"
                  cnxorg:version-at-this-collection-version="1.17">
        <md:title>Add and Subtract Mixed Numbers</md:title>
        
        
        
      </col:module>
        
      
    
    
      <col:module document="m53044" version="latest"
                  repository="https://legacy.cnx.org/content"
                  cnxorg:version-at-this-collection-version="1.26">
        <md:title>Solve Equations with Fractions</md:title>
        
        
        
      </col:module>
        
      
    
        </col:content>
      </col:subcollection>
    
    
      
        
      <col:subcollection>
        <md:title>Decimals</md:title>
        
        
        

        <col:content>
          
    
      <col:module document="m57796" version="latest"
                  repository="https://legacy.cnx.org/content"
                  cnxorg:version-at-this-collection-version="1.6">
        <md:title>Introduction to Decimals</md:title>
        
        
        
      </col:module>
        
      
    
    
      <col:module document="m53061" version="latest"
                  repository="https://legacy.cnx.org/content"
                  cnxorg:version-at-this-collection-version="1.18">
        <md:title>Decimals</md:title>
        
        
        
      </col:module>
        
      
    
    
      <col:module document="m53047" version="latest"
                  repository="https://legacy.cnx.org/content"
                  cnxorg:version-at-this-collection-version="1.17">
        <md:title>Decimal Operations</md:title>
        
        
        
      </col:module>
        
      
    
    
      <col:module document="m53052" version="latest"
                  repository="https://legacy.cnx.org/content"
                  cnxorg:version-at-this-collection-version="1.20">
        <md:title>Decimals and Fractions</md:title>
        
        
        
      </col:module>
        
      
    
    
      <col:module document="m53055" version="latest"
                  repository="https://legacy.cnx.org/content"
                  cnxorg:version-at-this-collection-version="1.17">
        <md:title>Solve Equations with Decimals</md:title>
        
        
        
      </col:module>
        
      
    
    
      <col:module document="m53060" version="latest"
                  repository="https://legacy.cnx.org/content"
                  cnxorg:version-at-this-collection-version="1.16">
        <md:title>Averages and Probability</md:title>
        
        
        
      </col:module>
        
      
    
    
      <col:module document="m53068" version="latest"
                  repository="https://legacy.cnx.org/content"
                  cnxorg:version-at-this-collection-version="1.12">
        <md:title>Ratios and Rate</md:title>
        
        
        
      </col:module>
        
      
    
    
      <col:module document="m53065" version="latest"
                  repository="https://legacy.cnx.org/content"
                  cnxorg:version-at-this-collection-version="1.21">
        <md:title>Simplify and Use Square Roots</md:title>
        
        
        
      </col:module>
        
      
    
        </col:content>
      </col:subcollection>
    
    
      
        
      <col:subcollection>
        <md:title>Percents</md:title>
        
        
        

        <col:content>
          
    
      <col:module document="m57797" version="latest"
                  repository="https://legacy.cnx.org/content"
                  cnxorg:version-at-this-collection-version="1.6">
        <md:title>Introduction to Percents</md:title>
        
        
        
      </col:module>
        
      
    
    
      <col:module document="m53077" version="latest"
                  repository="https://legacy.cnx.org/content"
                  cnxorg:version-at-this-collection-version="1.22">
        <md:title>Understand Percent</md:title>
        
        
        
      </col:module>
        
      
    
    
      <col:module document="m53086" version="latest"
                  repository="https://legacy.cnx.org/content"
                  cnxorg:version-at-this-collection-version="1.20">
        <md:title>Solve General Applications of Percent</md:title>
        
        
        
      </col:module>
        
      
    
    
      <col:module document="m53073" version="latest"
                  repository="https://legacy.cnx.org/content"
                  cnxorg:version-at-this-collection-version="1.23">
        <md:title>Solve Sales Tax, Commission, and Discount Applications</md:title>
        
        
        
      </col:module>
        
      
    
    
      <col:module document="m53075" version="latest"
                  repository="https://legacy.cnx.org/content"
                  cnxorg:version-at-this-collection-version="1.22">
        <md:title>Solve Simple Interest Applications</md:title>
        
        
        
      </col:module>
        
      
    
    
      <col:module document="m53082" version="latest"
                  repository="https://legacy.cnx.org/content"
                  cnxorg:version-at-this-collection-version="1.31">
        <md:title>Solve Proportions and their Applications</md:title>
        
        
        
      </col:module>
        
      
    
        </col:content>
      </col:subcollection>
    
    
      
        
      <col:subcollection>
        <md:title>The Properties of Real Numbers</md:title>
        
        
        

        <col:content>
          
    
      <col:module document="m57798" version="latest"
                  repository="https://legacy.cnx.org/content"
                  cnxorg:version-at-this-collection-version="1.6">
        <md:title>Introduction to the Properties of Real Numbers</md:title>
        
        
        
      </col:module>
        
      
    
    
      <col:module document="m53093" version="latest"
                  repository="https://legacy.cnx.org/content"
                  cnxorg:version-at-this-collection-version="1.17">
        <md:title>Rational and Irrational Numbers</md:title>
        
        
        
      </col:module>
        
      
    
    
      <col:module document="m53090" version="latest"
                  repository="https://legacy.cnx.org/content"
                  cnxorg:version-at-this-collection-version="1.15">
        <md:title>Commutative and Associative Properties</md:title>
        
        
        
      </col:module>
        
      
    
    
      <col:module document="m53099" version="latest"
                  repository="https://legacy.cnx.org/content"
                  cnxorg:version-at-this-collection-version="1.15">
        <md:title>Distributive Property</md:title>
        
        
        
      </col:module>
        
      
    
    
      <col:module document="m53106" version="latest"
                  repository="https://legacy.cnx.org/content"
                  cnxorg:version-at-this-collection-version="1.14">
        <md:title>Properties of Identity, Inverses, and Zero</md:title>
        
        
        
      </col:module>
        
      
    
    
      <col:module document="m53109" version="latest"
                  repository="https://legacy.cnx.org/content"
                  cnxorg:version-at-this-collection-version="1.18">
        <md:title>Systems of Measurement</md:title>
        
        
        
      </col:module>
        
      
    
        </col:content>
      </col:subcollection>
    
    
      
        
      <col:subcollection>
        <md:title>Solving Linear Equations</md:title>
        
        
        

        <col:content>
          
    
      <col:module document="m57799" version="latest"
                  repository="https://legacy.cnx.org/content"
                  cnxorg:version-at-this-collection-version="1.5">
        <md:title>Introduction to Solving Linear Equations</md:title>
        
        
        
      </col:module>
        
      
    
    
      <col:module document="m53111" version="latest"
                  repository="https://legacy.cnx.org/content"
                  cnxorg:version-at-this-collection-version="1.16">
        <md:title>Solve Equations Using the Subtraction and Addition Properties of Equality</md:title>
        
        
        
      </col:module>
        
      
    
    
      <col:module document="m53116" version="latest"
                  repository="https://legacy.cnx.org/content"
                  cnxorg:version-at-this-collection-version="1.15">
        <md:title>Solve Equations Using the Division and Multiplication Properties of Equality</md:title>
        
        
        
      </col:module>
        
      
    
    
      <col:module document="m53124" version="latest"
                  repository="https://legacy.cnx.org/content"
                  cnxorg:version-at-this-collection-version="1.15">
        <md:title>Solve Equations with Variables and Constants on Both Sides</md:title>
        
        
        
      </col:module>
        
      
    
    
      <col:module document="m53130" version="latest"
                  repository="https://legacy.cnx.org/content"
                  cnxorg:version-at-this-collection-version="1.18">
        <md:title>Solve Equations with Fraction or Decimal Coefficients</md:title>
        
        
        
      </col:module>
        
      
    
        </col:content>
      </col:subcollection>
    
    
      
        
      <col:subcollection>
        <md:title>Math Models and Geometry</md:title>
        
        
        

        <col:content>
          
    
      <col:module document="m57800" version="latest"
                  repository="https://legacy.cnx.org/content"
                  cnxorg:version-at-this-collection-version="1.6">
        <md:title>Introduction</md:title>
        
        
        
      </col:module>
        
      
    
    
      <col:module document="m53148" version="latest"
                  repository="https://legacy.cnx.org/content"
                  cnxorg:version-at-this-collection-version="1.19">
        <md:title>Use a Problem Solving Strategy</md:title>
        
        
        
      </col:module>
        
      
    
    
      <col:module document="m53134" version="latest"
                  repository="https://legacy.cnx.org/content"
                  cnxorg:version-at-this-collection-version="1.15">
        <md:title>Solve Money Applications</md:title>
        
        
        
      </col:module>
        
      
    
    
      <col:module document="m53137" version="latest"
                  repository="https://legacy.cnx.org/content"
                  cnxorg:version-at-this-collection-version="1.22">
        <md:title>Use Properties of Angles, Triangles, and the Pythagorean Theorem</md:title>
        
        
        
      </col:module>
        
      
    
    
      <col:module document="m53141" version="latest"
                  repository="https://legacy.cnx.org/content"
                  cnxorg:version-at-this-collection-version="1.22">
        <md:title>Use Properties of Rectangles, Triangles, and Trapezoids</md:title>
        
        
        
      </col:module>
        
      
    
    
      <col:module document="m53144" version="latest"
                  repository="https://legacy.cnx.org/content"
                  cnxorg:version-at-this-collection-version="1.20">
        <md:title>Solve Geometry Applications: Circles and Irregular Figures</md:title>
        
        
        
      </col:module>
        
      
    
    
      <col:module document="m53151" version="latest"
                  repository="https://legacy.cnx.org/content"
                  cnxorg:version-at-this-collection-version="1.19">
        <md:title>Solve Geometry Applications: Volume and Surface Area</md:title>
        
        
        
      </col:module>
        
      
    
    
      <col:module document="m53150" version="latest"
                  repository="https://legacy.cnx.org/content"
                  cnxorg:version-at-this-collection-version="1.22">
        <md:title>Solve a Formula for a Specific Variable</md:title>
        
        
        
      </col:module>
        
      
    
        </col:content>
      </col:subcollection>
    
    
      
        
      <col:subcollection>
        <md:title>Polynomials</md:title>
        
        
        

        <col:content>
          
    
      <col:module document="m57801" version="latest"
                  repository="https://legacy.cnx.org/content"
                  cnxorg:version-at-this-collection-version="1.5">
        <md:title>Introduction to Polynomials</md:title>
        
        
        
      </col:module>
        
      
    
    
      <col:module document="m53161" version="latest"
                  repository="https://legacy.cnx.org/content"
                  cnxorg:version-at-this-collection-version="1.20">
        <md:title>Add and Subtract Polynomials</md:title>
        
        
        
      </col:module>
        
      
    
    
      <col:module document="m53163" version="latest"
                  repository="https://legacy.cnx.org/content"
                  cnxorg:version-at-this-collection-version="1.18">
        <md:title>Use Multiplication Properties of Exponents</md:title>
        
        
        
      </col:module>
        
      
    
    
      <col:module document="m53164" version="latest"
                  repository="https://legacy.cnx.org/content"
                  cnxorg:version-at-this-collection-version="1.17">
        <md:title>Multiply Polynomials</md:title>
        
        
        
      </col:module>
        
      
    
    
      <col:module document="m53166" version="latest"
                  repository="https://legacy.cnx.org/content"
                  cnxorg:version-at-this-collection-version="1.18">
        <md:title>Divide Monomials</md:title>
        
        
        
      </col:module>
        
      
    
    
      <col:module document="m53167" version="latest"
                  repository="https://legacy.cnx.org/content"
                  cnxorg:version-at-this-collection-version="1.20">
        <md:title>Integer Exponents and Scientific Notation</md:title>
        
        
        
      </col:module>
        
      
    
    
      <col:module document="m53168" version="latest"
                  repository="https://legacy.cnx.org/content"
                  cnxorg:version-at-this-collection-version="1.19">
        <md:title>Introduction to Factoring Polynomials</md:title>
        
        
        
      </col:module>
        
      
    
        </col:content>
      </col:subcollection>
    
    
      
        
      <col:subcollection>
        <md:title>Graphs</md:title>
        
        
        

        <col:content>
          
    
      <col:module document="m57803" version="latest"
                  repository="https://legacy.cnx.org/content"
                  cnxorg:version-at-this-collection-version="1.6">
        <md:title>Graphs</md:title>
        
        
        
      </col:module>
        
      
    
    
      <col:module document="m53173" version="latest"
                  repository="https://legacy.cnx.org/content"
                  cnxorg:version-at-this-collection-version="1.22">
        <md:title>Use the Rectangular Coordinate System</md:title>
        
        
        
      </col:module>
        
      
    
    
      <col:module document="m53180" version="latest"
                  repository="https://legacy.cnx.org/content"
                  cnxorg:version-at-this-collection-version="1.21">
        <md:title>Graphing Linear Equations</md:title>
        
        
        
      </col:module>
        
      
    
    
      <col:module document="m53183" version="latest"
                  repository="https://legacy.cnx.org/content"
                  cnxorg:version-at-this-collection-version="1.24">
        <md:title>Graphing with Intercepts</md:title>
        
        
        
      </col:module>
        
      
    
    
      <col:module document="m53185" version="latest"
                  repository="https://legacy.cnx.org/content"
                  cnxorg:version-at-this-collection-version="1.22">
        <md:title>Understand Slope of a Line</md:title>
        
        
        
      </col:module>
        
      
    
        </col:content>
      </col:subcollection>
    
    
      <col:module document="m56252" version="latest"
                  repository="https://legacy.cnx.org/content"
                  cnxorg:version-at-this-collection-version="1.9">
        <md:title>Cumulative Review</md:title>
        
        
        
      </col:module>
        
      
    
    
      <col:module document="m56244" version="latest"
                  repository="https://legacy.cnx.org/content"
                  cnxorg:version-at-this-collection-version="1.5">
        <md:title>Powers and Roots Tables</md:title>
        
        
        
      </col:module>
        
      
    
    
      <col:module document="m56248" version="latest"
                  repository="https://legacy.cnx.org/content"
                  cnxorg:version-at-this-collection-version="1.5">
        <md:title>Geometric Formulas</md:title>
        
        
        
      </col:module>
        
      
    
  </col:content>
</col:collection>
